salesforcecdpconnector/__init__.py
salesforcecdpconnector/authentication_helper.py
salesforcecdpconnector/connection.py
salesforcecdpconnector/constants.py
salesforcecdpconnector/cursor.py
salesforcecdpconnector/exceptions.py
salesforcecdpconnector/pandas_utils.py
salesforcecdpconnector/parsed_query_result.py
salesforcecdpconnector/query_result_parser.py
salesforcecdpconnector/query_submitter.py
cdp_connector-1.0.2.dist-info/LICENSE.txt
cdp_connector-1.0.2.dist-info/METADATA
cdp_connector-1.0.2.dist-info/WHEEL
cdp_connector-1.0.2.dist-info/top_level.txt
cdp_connector-1.0.2.dist-info/RECORD
