Metadata-Version: 2.1
Name: cdp-connector
Version: 1.0.2
Summary: Python Connector for Salesforce CDP
Home-page: https://github.com/forcedotcom/cdp-connector
Author: Vishnu Prasad
License: BSD-3-Clause
Keywords: cdp,salesforce,dbapi
Platform: UNKNOWN
Requires-Python: <3.10,>=3.8
License-File: LICENSE.txt
Requires-Dist: certifi (==2021.10.8)
Requires-Dist: charset-normalizer (==2.0.10)
Requires-Dist: idna (==3.3)
Requires-Dist: numpy (==1.21.4,==1.22.2)
Requires-Dist: pandas (==1.3.5)
Requires-Dist: pip (==22.0.4)
Requires-Dist: pyarrow (==4.0.0)
Requires-Dist: python-dateutil (==2.8.2)
Requires-Dist: pytz (==2021.3)
Requires-Dist: requests (==2.27.1)
Requires-Dist: responses (==0.16.0)
Requires-Dist: setuptools (==60.9.3)
Requires-Dist: six (==1.16.0)
Requires-Dist: urllib3 (==1.26.8)
Requires-Dist: wheel (==0.37.1)
